galts_trade_api/__init__.py
galts_trade_api/asset.py
galts_trade_api/asyncio_helper.py
galts_trade_api/exchange.py
galts_trade_api/structlogger.py
galts_trade_api/terminal.py
galts_trade_api/tools.py
galts_trade_api/transport/__init__.py
galts_trade_api/transport/exchange_info_client.py
galts_trade_api/transport/grpc_utils.py
galts_trade_api/transport/real.py
galts_trade_api/transport/protos/__init__.py
galts_trade_api/transport/protos/common.proto
galts_trade_api/transport/protos/common_pb2.py
galts_trade_api/transport/protos/exchange_info/__init__.py
galts_trade_api/transport/protos/exchange_info/api.proto
galts_trade_api/transport/protos/exchange_info/api_pb2.py
galts_trade_api/transport/protos/exchange_info/api_pb2_grpc.py
galts_trade_api/transport/protos/exchange_info/entities.proto
galts_trade_api/transport/protos/exchange_info/entities_pb2.py
galts_trade_api-0.2.0.dist-info/LICENSE
galts_trade_api-0.2.0.dist-info/METADATA
galts_trade_api-0.2.0.dist-info/WHEEL
galts_trade_api-0.2.0.dist-info/top_level.txt
galts_trade_api-0.2.0.dist-info/RECORD
