Metadata-Version: 2.1
Name: galts-trade-api
Version: 0.2.0
Summary: A framework to use a trading infrastructure
Home-page: UNKNOWN
Author: Sergey Nevmerzhitsky
Author-email: sergey.nevmerzhitsky@gmail.com
License: Mozilla Public License 2.0
Keywords: crypto,trading
Platform: UNKNOWN
Classifier: Development Status :: 4 - Beta
Classifier: Intended Audience :: Financial and Insurance Industry
Classifier: License :: OSI Approved :: Mozilla Public License 2.0 (MPL 2.0)
Classifier: Operating System :: OS Independent
Classifier: Programming Language :: Python :: 3
Classifier: Programming Language :: Python :: 3.7
Requires-Python: ~=3.7
Requires-Dist: aio-pika (~=5.0)
Requires-Dist: grpcio (~=1.20)
Requires-Dist: protobuf (~=3.11)
Requires-Dist: structlog (~=19.2.0)
Requires-Dist: ujson (~=1.35)
